quickpathstr/__init__.py
quickpathstr/quickpathstr.py
quickpathstr/tests/test.py
quickpathstr-0.0.4.dist-info/METADATA
quickpathstr-0.0.4.dist-info/WHEEL
quickpathstr-0.0.4.dist-info/RECORD
