Metadata-Version: 2.1
Name: quickpathstr
Version: 0.0.4
Summary: Provides syntax for working with strings in the context of file management.
Project-URL: GitHub, https://github.com/SeanYeatts/quickpathstr.git
Author: Sean Yeatts
Classifier: License :: OSI Approved :: MIT License
Classifier: Operating System :: OS Independent
Classifier: Programming Language :: Python :: 3
Requires-Python: >=3.7
